cfg_mgmt/__init__.py
cfg_mgmt/alicloud.py
cfg_mgmt/aws.py
cfg_mgmt/azure.py
cfg_mgmt/btp_application_certificate.py
cfg_mgmt/btp_service_binding.py
cfg_mgmt/gcp.py
cfg_mgmt/github.py
cfg_mgmt/kubernetes.py
cfg_mgmt/metrics.py
cfg_mgmt/model.py
cfg_mgmt/reporting.py
cfg_mgmt/rotate.py
cfg_mgmt/util.py
gardener_cicd_cfg_mgmt-1.2614.0.dist-info/LICENSE
gardener_cicd_cfg_mgmt-1.2614.0.dist-info/METADATA
gardener_cicd_cfg_mgmt-1.2614.0.dist-info/WHEEL
gardener_cicd_cfg_mgmt-1.2614.0.dist-info/top_level.txt
gardener_cicd_cfg_mgmt-1.2614.0.dist-info/RECORD
